{"status":"OK","copyright":"Copyright (c) 2021 The New York Times Company.  All Rights Reserved.","num_results":10,"last_modified":"2021-02-11T17:06:12-05:00","results":{"list_name":"Childrens Middle Grade Hardcover","list_name_encoded":"childrens-middle-grade-hardcover","bestsellers_date":"2021-02-06","published_date":"2021-02-21","published_date_description":"latest","next_published_date":"","previous_published_date":"2021-02-14","display_name":"Children\u2019s Middle Grade Hardcover","normal_list_ends_at":10,"updated":"WEEKLY","books":[{"rank":1,"rank_last_week":0,"weeks_on_list":1,"asterisk":0,"dagger":0,"primary_isbn10":"1338245759","primary_isbn13":"9781338245752","publisher":"Scholastic","description":"Parallel storylines of Brandon and Reshmina take place on Sept. 11th, in 2001 and 2019.","price":"0.00","title":"GROUND ZERO","author":"Alan Gratz","contributor":"by Alan Gratz","contributor_note":"","book_image":"https:\/\/storage.googleapis.com\/du-prd\/books\/images\/9781338245752.jpg","book_image_width":331,"book_image_height":500,"amazon_product_url":"https:\/\/www.amazon.com\/dp\/1338245759?tag=NYTBSREV-20&tag=NYTBSREV-20","age_group":"","book_review_link":"","first_chapter_link":"","sunday_review_link":"","article_chapter_link":"","isbns":[{"isbn10":"1338245759","isbn13":"9781338245752"}],"buy_links":[{"name":"Amazon","url":"https:\/\/www.amazon.com\/dp\/1338245759?tag=NYTBSREV-20&tag=NYTBSREV-20"},{"name":"Apple Books","url":"https:\/\/du-gae-books-dot-nyt-du-prd.appspot.com\/buy?title=GROUND+ZERO&author=Alan+Gratz"},{"name":"Barnes and Noble","url":"https:\/\/www.anrdoezrs.net\/click-7990613-11819508?url=https%3A%2F%2Fwww.barnesandnoble.com%2Fw%2F%3Fean%3D9781338245752"},{"name":"Books-A-Million","url":"https:\/\/www.anrdoezrs.net\/click-7990613-35140?url=https%3A%2F%2Fwww.booksamillion.com%2Fp%2FGROUND%2BZERO%2FAlan%2BGratz%2F9781338245752"},{"name":"Bookshop","url":"https:\/\/bookshop.org\/a\/3546\/9781338245752"},{"name":"Indiebound","url":"https:\/\/www.indiebound.org\/book\/9781338245752?aff=NYT"}],"book_uri":"nyt:\/\/book\/93e9d008-544b-581f-9681-75c147c79a93"},{"rank":2,"rank_last_week":1,"weeks_on_list":13,"asterisk":0,"dagger":0,"primary_isbn10":"1338732870","primary_isbn13":"9781338732870","publisher":"Scholastic","description":"A fearsome monster threatens the kingdom of Cornucopia.","price":"0.00","title":"THE ICKABOG","author":"J.K. Rowling","contributor":"by J.K. Rowling","contributor_note":"","book_image":"https:\/\/storage.googleapis.com\/du-prd\/books\/images\/9781338732870.jpg","book_image_width":337,"book_image_height":500,"amazon_product_url":"https:\/\/www.amazon.com\/dp\/1338732870?tag=NYTBSREV-20&tag=NYTBSREV-20","age_group":"","book_review_link":"","first_chapter_link":"","sunday_review_link":"","article_chapter_link":"","isbns":[{"isbn10":"1338732870","isbn13":"9781338732870"}],"buy_links":[{"name":"Amazon","url":"https:\/\/www.amazon.com\/dp\/1338732870?tag=NYTBSREV-20&tag=NYTBSREV-20"},{"name":"Apple Books","url":"https:\/\/du-gae-books-dot-nyt-du-prd.appspot.com\/buy?title=THE+ICKABOG&author=J.K.+Rowling"},{"name":"Barnes and Noble","url":"https:\/\/www.anrdoezrs.net\/click-7990613-11819508?url=https%3A%2F%2Fwww.barnesandnoble.com%2Fw%2F%3Fean%3D9781338732870"},{"name":"Books-A-Million","url":"https:\/\/www.anrdoezrs.net\/click-7990613-35140?url=https%3A%2F%2Fwww.booksamillion.com%2Fp%2FTHE%2BICKABOG%2FJ.K.%2BRowling%2F9781338732870"},{"name":"Bookshop","url":"https:\/\/bookshop.org\/a\/3546\/9781338732870"},{"name":"Indiebound","url":"https:\/\/www.indiebound.org\/book\/9781338732870?aff=NYT"}],"book_uri":"nyt:\/\/book\/9c1873f5-0249-5f05-9a48-ae5745cfe4ac"},{"rank":3,"rank_last_week":2,"weeks_on_list":54,"asterisk":0,"dagger":0,"primary_isbn10":"0316475114","primary_isbn13":"9780316475112","publisher":"Little, Brown","description":"The biographies of 40 African-American women who made a difference.","price":"0.00","title":"LITTLE LEADERS","author":"Vashti Harrison","contributor":"by Vashti Harrison","contributor_note":"","book_image":"https:\/\/storage.googleapis.com\/du-prd\/books\/images\/9780316475112.jpg","book_image_width":330,"book_image_height":410,"amazon_product_url":"https:\/\/www.amazon.com\/Little-Leaders-Women-Black-History\/dp\/0316475114?tag=NYTBSREV-20","age_group":"","book_review_link":"","first_chapter_link":"","sunday_review_link":"","article_chapter_link":"","isbns":[{"isbn10":"0316475114","isbn13":"9780316475112"}],"buy_links":[{"name":"Amazon","url":"https:\/\/www.amazon.com\/Little-Leaders-Women-Black-History\/dp\/0316475114?tag=NYTBSREV-20"},{"name":"Apple Books","url":"https:\/\/du-gae-books-dot-nyt-du-prd.appspot.com\/buy?title=LITTLE+LEADERS&author=Vashti+Harrison"},{"name":"Barnes and Noble","url":"https:\/\/www.anrdoezrs.net\/click-7990613-11819508?url=https%3A%2F%2Fwww.barnesandnoble.com%2Fw%2F%3Fean%3D9780316475112"},{"name":"Books-A-Million","url":"https:\/\/www.anrdoezrs.net\/click-7990613-35140?url=https%3A%2F%2Fwww.booksamillion.com%2Fp%2FLITTLE%2BLEADERS%2FVashti%2BHarrison%2F9780316475112"},{"name":"Bookshop","url":"https:\/\/bookshop.org\/a\/3546\/9780316475112"},{"name":"Indiebound","url":"https:\/\/www.indiebound.org\/book\/9780316475112?aff=NYT"}],"book_uri":"nyt:\/\/book\/cb51822f-0f9a-52c8-b301-1d6961a45ab3"},{"rank":4,"rank_last_week":3,"weeks_on_list":20,"asterisk":0,"dagger":0,"primary_isbn10":"0316475149","primary_isbn13":"9780316475143","publisher":"Little, Brown","description":"Biographies of trailblazing Black men.","price":"0.00","title":"LITTLE LEGENDS: EXCEPTIONAL MEN IN BLACK HISTORY","author":"Vashti Harrison with Kwesi Johnson","contributor":"by Vashti Harrison with Kwesi Johnson","contributor_note":"","book_image":"https:\/\/storage.googleapis.com\/du-prd\/books\/images\/9780316475143.jpg","book_image_width":330,"book_image_height":396,"amazon_product_url":"https:\/\/www.amazon.com\/Little-Legends-Exceptional-Black-History\/dp\/0316475149?tag=NYTBSREV-20","age_group":"","book_review_link":"","first_chapter_link":"","sunday_review_link":"","article_chapter_link":"","isbns":[{"isbn10":"0316475149","isbn13":"9780316475143"}],"buy_links":[{"name":"Amazon","url":"https:\/\/www.amazon.com\/Little-Legends-Exceptional-Black-History\/dp\/0316475149?tag=NYTBSREV-20"},{"name":"Apple Books","url":"https:\/\/du-gae-books-dot-nyt-du-prd.appspot.com\/buy?title=LITTLE+LEGENDS%3A+EXCEPTIONAL+MEN+IN+BLACK+HISTORY&author=Vashti+Harrison+with+Kwesi+Johnson"},{"name":"Barnes and Noble","url":"https:\/\/www.anrdoezrs.net\/click-7990613-11819508?url=https%3A%2F%2Fwww.barnesandnoble.com%2Fw%2F%3Fean%3D9780316475143"},{"name":"Books-A-Million","url":"https:\/\/www.anrdoezrs.net\/click-7990613-35140?url=https%3A%2F%2Fwww.booksamillion.com%2Fp%2FLITTLE%2BLEGENDS%253A%2BEXCEPTIONAL%2BMEN%2BIN%2BBLACK%2BHISTORY%2FVashti%2BHarrison%2Bwith%2BKwesi%2BJohnson%2F9780316475143"},{"name":"Bookshop","url":"https:\/\/bookshop.org\/a\/3546\/9780316475143"},{"name":"Indiebound","url":"https:\/\/www.indiebound.org\/book\/9780316475143?aff=NYT"}],"book_uri":"nyt:\/\/book\/3112d1e2-bf19-5757-bf03-53403a100e6c"},{"rank":5,"rank_last_week":4,"weeks_on_list":27,"asterisk":0,"dagger":0,"primary_isbn10":"1419749099","primary_isbn13":"9781419749094","publisher":"Amulet","description":"Roland and Garg the Barbarian embark on a quest to save Roland's mom from the White Warlock.","price":"0.00","title":"ROWLEY JEFFERSON'S AWESOME FRIENDLY ADVENTURE","author":"Jeff Kinney","contributor":"by Jeff Kinney","contributor_note":"","book_image":"https:\/\/storage.googleapis.com\/du-prd\/books\/images\/9781419749094.jpg","book_image_width":341,"book_image_height":500,"amazon_product_url":"https:\/\/www.amazon.com\/dp\/1419749099?tag=NYTBSREV-20&tag=NYTBSREV-20","age_group":"","book_review_link":"","first_chapter_link":"","sunday_review_link":"","article_chapter_link":"","isbns":[{"isbn10":"1419749099","isbn13":"9781419749094"}],"buy_links":[{"name":"Amazon","url":"https:\/\/www.amazon.com\/dp\/1419749099?tag=NYTBSREV-20&tag=NYTBSREV-20"},{"name":"Apple Books","url":"https:\/\/du-gae-books-dot-nyt-du-prd.appspot.com\/buy?title=ROWLEY+JEFFERSON%27S+AWESOME+FRIENDLY+ADVENTURE&author=Jeff+Kinney"},{"name":"Barnes and Noble","url":"https:\/\/www.anrdoezrs.net\/click-7990613-11819508?url=https%3A%2F%2Fwww.barnesandnoble.com%2Fw%2F%3Fean%3D9781419749094"},{"name":"Books-A-Million","url":"https:\/\/www.anrdoezrs.net\/click-7990613-35140?url=https%3A%2F%2Fwww.booksamillion.com%2Fp%2FROWLEY%2BJEFFERSON%2527S%2BAWESOME%2BFRIENDLY%2BADVENTURE%2FJeff%2BKinney%2F9781419749094"},{"name":"Bookshop","url":"https:\/\/bookshop.org\/a\/3546\/9781419749094"},{"name":"Indiebound","url":"https:\/\/www.indiebound.org\/book\/9781419749094?aff=NYT"}],"book_uri":"nyt:\/\/book\/0f198b73-e6ac-51b5-87ee-a33e0984a379"},{"rank":6,"rank_last_week":9,"weeks_on_list":2,"asterisk":0,"dagger":0,"primary_isbn10":"1524715700","primary_isbn13":"9781524715700","publisher":"Random House","description":"Lily makes a deal with a magical tiger to heal her ailing grandmother.","price":"0.00","title":"WHEN YOU TRAP A TIGER","author":"Tae Keller","contributor":"by Tae Keller","contributor_note":"","book_image":"https:\/\/storage.googleapis.com\/du-prd\/books\/images\/9781524715700.jpg","book_image_width":330,"book_image_height":500,"amazon_product_url":"https:\/\/www.amazon.com\/dp\/1524715700?tag=NYTBSREV-20&tag=NYTBSREV-20","age_group":"","book_review_link":"","first_chapter_link":"","sunday_review_link":"","article_chapter_link":"","isbns":[{"isbn10":"1524715700","isbn13":"9781524715700"}],"buy_links":[{"name":"Amazon","url":"https:\/\/www.amazon.com\/dp\/1524715700?tag=NYTBSREV-20&tag=NYTBSREV-20"},{"name":"Apple Books","url":"https:\/\/du-gae-books-dot-nyt-du-prd.appspot.com\/buy?title=WHEN+YOU+TRAP+A+TIGER&author=Tae+Keller"},{"name":"Barnes and Noble","url":"https:\/\/www.anrdoezrs.net\/click-7990613-11819508?url=https%3A%2F%2Fwww.barnesandnoble.com%2Fw%2F%3Fean%3D9781524715700"},{"name":"Books-A-Million","url":"https:\/\/www.anrdoezrs.net\/click-7990613-35140?url=https%3A%2F%2Fwww.booksamillion.com%2Fp%2FWHEN%2BYOU%2BTRAP%2BA%2BTIGER%2FTae%2BKeller%2F9781524715700"},{"name":"Bookshop","url":"https:\/\/bookshop.org\/a\/3546\/9781524715700"},{"name":"Indiebound","url":"https:\/\/www.indiebound.org\/book\/9781524715700?aff=NYT"}],"book_uri":"nyt:\/\/book\/3ce2d46d-ebf0-597e-9ab1-baadf6b5dd65"},{"rank":7,"rank_last_week":5,"weeks_on_list":283,"asterisk":0,"dagger":0,"primary_isbn10":"0375869026","primary_isbn13":"9780375869020","publisher":"Knopf","description":"A boy with a facial deformity starts school.","price":"0.00","title":"WONDER","author":"R.J. Palacio","contributor":"by R.J. Palacio","contributor_note":"","book_image":"https:\/\/storage.googleapis.com\/du-prd\/books\/images\/9780375899881.jpg","book_image_width":329,"book_image_height":495,"amazon_product_url":"http:\/\/www.amazon.com\/Wonder-R-J-Palacio-ebook\/dp\/B0051ANPZQ?tag=NYTBSREV-20","age_group":"","book_review_link":"","first_chapter_link":"","sunday_review_link":"https:\/\/www.nytimes.com\/2012\/04\/08\/books\/review\/wonder-by-r-j-palacio.html","article_chapter_link":"","isbns":[{"isbn10":"0375869026","isbn13":"9780375869020"},{"isbn10":"037589988X","isbn13":"9780375899881"},{"isbn10":"0375969020","isbn13":"9780375969027"},{"isbn10":"1524720194","isbn13":"9781524720193"},{"isbn10":"1524719773","isbn13":"9781524719777"}],"buy_links":[{"name":"Amazon","url":"http:\/\/www.amazon.com\/Wonder-R-J-Palacio-ebook\/dp\/B0051ANPZQ?tag=NYTBSREV-20"},{"name":"Apple Books","url":"https:\/\/du-gae-books-dot-nyt-du-prd.appspot.com\/buy?title=WONDER&author=R.J.+Palacio"},{"name":"Barnes and Noble","url":"https:\/\/www.anrdoezrs.net\/click-7990613-11819508?url=https%3A%2F%2Fwww.barnesandnoble.com%2Fw%2F%3Fean%3D9780375869020"},{"name":"Books-A-Million","url":"https:\/\/www.anrdoezrs.net\/click-7990613-35140?url=https%3A%2F%2Fwww.booksamillion.com%2Fp%2FWONDER%2FR.J.%2BPalacio%2F9780375869020"},{"name":"Bookshop","url":"https:\/\/bookshop.org\/a\/3546\/9780375869020"},{"name":"Indiebound","url":"https:\/\/www.indiebound.org\/book\/9780375869020?aff=NYT"}],"book_uri":"nyt:\/\/book\/ae6bd2cf-a5d7-535a-99dd-ca8e283c2b01"},{"rank":8,"rank_last_week":10,"weeks_on_list":89,"asterisk":0,"dagger":0,"primary_isbn10":"141974027X","primary_isbn13":"9781419740275","publisher":"Amulet","description":"Greg\u2019s best friend Rowley Jefferson writes his own diary.","price":"0.00","title":"DIARY OF AN AWESOME FRIENDLY KID","author":"Jeff Kinney","contributor":"by Jeff Kinney","contributor_note":"","book_image":"https:\/\/storage.googleapis.com\/du-prd\/books\/images\/9781419740275.jpg","book_image_width":330,"book_image_height":484,"amazon_product_url":"https:\/\/www.amazon.com\/Diary-Awesome-Friendly-Jeff-Kinney\/dp\/141974027X?tag=NYTBSREV-20","age_group":"","book_review_link":"","first_chapter_link":"","sunday_review_link":"","article_chapter_link":"","isbns":[{"isbn10":"141974027X","isbn13":"9781419740275"}],"buy_links":[{"name":"Amazon","url":"https:\/\/www.amazon.com\/Diary-Awesome-Friendly-Jeff-Kinney\/dp\/141974027X?tag=NYTBSREV-20"},{"name":"Apple Books","url":"https:\/\/du-gae-books-dot-nyt-du-prd.appspot.com\/buy?title=DIARY+OF+AN+AWESOME+FRIENDLY+KID&author=Jeff+Kinney"},{"name":"Barnes and Noble","url":"https:\/\/www.anrdoezrs.net\/click-7990613-11819508?url=https%3A%2F%2Fwww.barnesandnoble.com%2Fw%2F%3Fean%3D9781419740275"},{"name":"Books-A-Million","url":"https:\/\/www.anrdoezrs.net\/click-7990613-35140?url=https%3A%2F%2Fwww.booksamillion.com%2Fp%2FDIARY%2BOF%2BAN%2BAWESOME%2BFRIENDLY%2BKID%2FJeff%2BKinney%2F9781419740275"},{"name":"Bookshop","url":"https:\/\/bookshop.org\/a\/3546\/9781419740275"},{"name":"Indiebound","url":"https:\/\/www.indiebound.org\/book\/9781419740275?aff=NYT"}],"book_uri":"nyt:\/\/book\/2c334e8d-2b14-588a-9e43-98e5cad415ef"},{"rank":9,"rank_last_week":7,"weeks_on_list":40,"asterisk":0,"dagger":0,"primary_isbn10":"0062991310","primary_isbn13":"9780062991317","publisher":"HarperCollins","description":"In this sequel to \"The One and Only Ivan,\" Bob sets out on a dangerous journey in search of his long-lost sister.","price":"0.00","title":"THE ONE AND ONLY BOB","author":"Katherine Applegate.","contributor":"by Katherine Applegate. Illustrated by Patricia Castelao","contributor_note":"Illustrated by Patricia Castelao","book_image":"https:\/\/storage.googleapis.com\/du-prd\/books\/images\/9780062991317.jpg","book_image_width":352,"book_image_height":500,"amazon_product_url":"https:\/\/www.amazon.com\/dp\/0062991310?tag=NYTBSREV-20&tag=NYTBSREV-20","age_group":"","book_review_link":"","first_chapter_link":"","sunday_review_link":"","article_chapter_link":"","isbns":[{"isbn10":"0062991310","isbn13":"9780062991317"}],"buy_links":[{"name":"Amazon","url":"https:\/\/www.amazon.com\/dp\/0062991310?tag=NYTBSREV-20&tag=NYTBSREV-20"},{"name":"Apple Books","url":"https:\/\/du-gae-books-dot-nyt-du-prd.appspot.com\/buy?title=THE+ONE+AND+ONLY+BOB&author=Katherine+Applegate."},{"name":"Barnes and Noble","url":"https:\/\/www.anrdoezrs.net\/click-7990613-11819508?url=https%3A%2F%2Fwww.barnesandnoble.com%2Fw%2F%3Fean%3D9780062991317"},{"name":"Books-A-Million","url":"https:\/\/www.anrdoezrs.net\/click-7990613-35140?url=https%3A%2F%2Fwww.booksamillion.com%2Fp%2FTHE%2BONE%2BAND%2BONLY%2BBOB%2FKatherine%2BApplegate.%2F9780062991317"},{"name":"Bookshop","url":"https:\/\/bookshop.org\/a\/3546\/9780062991317"},{"name":"Indiebound","url":"https:\/\/www.indiebound.org\/book\/9780062991317?aff=NYT"}],"book_uri":"nyt:\/\/book\/490e07c0-9c8f-5eef-8463-cae65c42b46f"},{"rank":10,"rank_last_week":8,"weeks_on_list":2,"asterisk":0,"dagger":0,"primary_isbn10":"0062975161","primary_isbn13":"9780062975164","publisher":"Balzer + Bray","description":"Amari Peters competes for a spot at the Bureau of Supernatural Affairs.","price":"0.00","title":"AMARI AND THE NIGHT BROTHERS","author":"B.B. Alston","contributor":"by B.B. Alston","contributor_note":"","book_image":"https:\/\/storage.googleapis.com\/du-prd\/books\/images\/9780062975164.jpg","book_image_width":331,"book_image_height":500,"amazon_product_url":"https:\/\/www.amazon.com\/dp\/0062975161?tag=NYTBSREV-20&tag=NYTBSREV-20","age_group":"","book_review_link":"","first_chapter_link":"","sunday_review_link":"","article_chapter_link":"","isbns":[{"isbn10":"0062975161","isbn13":"9780062975164"}],"buy_links":[{"name":"Amazon","url":"https:\/\/www.amazon.com\/dp\/0062975161?tag=NYTBSREV-20&tag=NYTBSREV-20"},{"name":"Apple Books","url":"https:\/\/du-gae-books-dot-nyt-du-prd.appspot.com\/buy?title=AMARI+AND+THE+NIGHT+BROTHERS&author=B.B.+Alston"},{"name":"Barnes and Noble","url":"https:\/\/www.anrdoezrs.net\/click-7990613-11819508?url=https%3A%2F%2Fwww.barnesandnoble.com%2Fw%2F%3Fean%3D9780062975164"},{"name":"Books-A-Million","url":"https:\/\/www.anrdoezrs.net\/click-7990613-35140?url=https%3A%2F%2Fwww.booksamillion.com%2Fp%2FAMARI%2BAND%2BTHE%2BNIGHT%2BBROTHERS%2FB.B.%2BAlston%2F9780062975164"},{"name":"Bookshop","url":"https:\/\/bookshop.org\/a\/3546\/9780062975164"},{"name":"Indiebound","url":"https:\/\/www.indiebound.org\/book\/9780062975164?aff=NYT"}],"book_uri":"nyt:\/\/book\/a8bc13d6-e064-50ca-8f88-795a575da268"}],"corrections":[]}}